vecpot/__init__.py
vecpot/client.py
vecpot/exceptions.py
vecpot-0.1.1.dist-info/LICENSE.txt
vecpot-0.1.1.dist-info/METADATA
vecpot-0.1.1.dist-info/WHEEL
vecpot-0.1.1.dist-info/top_level.txt
vecpot-0.1.1.dist-info/RECORD
